rinkrat/__init__.py
rinkrat/__main__.py
rinkrat/api.py
rinkrat/cli.py
rinkrat/config.toml
rinkrat/standings.py
rinkrat-0.1.1.dist-info/LICENSE
rinkrat-0.1.1.dist-info/METADATA
rinkrat-0.1.1.dist-info/WHEEL
rinkrat-0.1.1.dist-info/entry_points.txt
rinkrat-0.1.1.dist-info/top_level.txt
rinkrat-0.1.1.dist-info/RECORD
