Metadata-Version: 2.1
Name: rinkrat
Version: 0.1.1
Summary: A command line tool to query NHL stats.
Author: Alex Reynolds
Project-URL: Homepage, https://github.com/reyncode/rinkrat.git
Project-URL: Issues, https://github.com/reyncode/rinkrat/issues
Keywords: NHL,hockey,stats
Classifier: Topic :: Utilities
Classifier: Programming Language :: Python
Classifier: Programming Language :: Python :: 3
Classifier: Programming Language :: Python :: 3 :: Only
Classifier: Environment :: Console
Classifier: Operating System :: OS Independent
Requires-Python: >=3.8
License-File: LICENSE
Requires-Dist: requests >=2.31.0
Requires-Dist: requests-cache >=1.1.1
Requires-Dist: tomli ; python_version < "3.11"
Provides-Extra: build
Requires-Dist: build ; extra == 'build'
Requires-Dist: twine ; extra == 'build'
Provides-Extra: dev
Requires-Dist: pip-tools ; extra == 'dev'
Requires-Dist: pytest ; extra == 'dev'
Requires-Dist: bumpver ; extra == 'dev'
